<?xml version="1.0" encoding="UTF-8" standalone="no" ?><alarm>
  <alarmname>OneWayAudioRecording</alarmname>
  <alarminstanceid>5557862112</alarminstanceid>
  <componentname>IPCaptureEngine</componentname>
  <parameters>
    <parameter>goxsa5187</parameter>
    <parameter>SIP/48645719@SEPBCF1F2E8EF21</parameter>
    <parameter>5557862112</parameter>
    <parameter>GO Phones</parameter>
    <parameter>588010008166213</parameter>
    <parameter>10.131.51.141</parameter>
    <parameter>10.131.51.141:0 -) 10.147.16.201:53520;</parameter>
</parameters>
  <triggertime initial="2018-05-23T20:56:55.100Z">2018-05-25T20:17:59.390Z</triggertime>
  <priorityvalue>3</priorityvalue>
  <priorityname>Major</priorityname>
  <perfalarm>No</perfalarm>
</alarm>
